{
  "page_id": "page_0035_MainActivity",
  "label": "点击'unknown'后",
  "timestamp": "2026-06-25T22:13:57.184862",
  "activity_info": {
    "resumed_activity": "topResumedActivity=ActivityRecord{132008040 u0 com.whaticancook.app.debug/com.whaticancook.app.MainActivity t124}",
    "current_focus": "mCurrentFocus=Window{ac65f2b u0 com.whaticancook.app.debug/com.whaticancook.app.MainActivity}"
  },
  "clickable_count": 66,
  "clickable_elements": [
    {
      "class": "android.view.View",
      "text": "",
      "resource-id": "",
      "content-desc": "",
      "bounds": "[60,87][1284,116]",
      "center": [
        672,
        101
      ],
      "long-clickable": false,
      "scroll_index": 0
    },
    {
      "class": "android.view.View",
      "text": "🍳",
      "resource-id": "",
      "content-desc": "",
      "bounds": "[60,176][1284,994]",
      "center": [
        672,
        585
      ],
      "long-clickable": false,
      "scroll_index": 0
    },
    {
      "class": "android.view.View",
      "text": "",
      "resource-id": "",
      "content-desc": "",
      "bounds": "[1122,194][1266,338]",
      "center": [
        1194,
        266
      ],
      "long-clickable": false,
      "scroll_index": 0
    },
    {
      "class": "android.view.View",
      "text": "🍤",
      "resource-id": "",
      "content-desc": "",
      "bounds": "[60,1054][1284,1872]",
      "center": [
        672,
        1463
      ],
      "long-clickable": false,
      "scroll_index": 0
    },
    {
      "class": "android.view.View",
      "text": "",
      "resource-id": "",
      "content-desc": "",
      "bounds": "[1122,1072][1266,1216]",
      "center": [
        1194,
        1144
      ],
      "long-clickable": false,
      "scroll_index": 0
    },
    {
      "class": "android.view.View",
      "text": "🍝",
      "resource-id": "",
      "content-desc": "",
      "bounds": "[60,1932][1284,2740]",
      "center": [
        672,
        2336
      ],
      "long-clickable": false,
      "scroll_index": 0
    },
    {
      "class": "android.view.View",
      "text": "",
      "resource-id": "",
      "content-desc": "",
      "bounds": "[1122,1950][1266,2094]",
      "center": [
        1194,
        2022
      ],
      "long-clickable": false,
      "scroll_index": 0
    },
    {
      "class": "android.view.View",
      "text": "Discover",
      "resource-id": "",
      "content-desc": "",
      "bounds": "[84,2722][452,2866]",
      "center": [
        268,
        2794
      ],
      "long-clickable": false,
      "scroll_index": 0
    },
    {
      "class": "android.view.View",
      "text": "",
      "resource-id": "",
      "content-desc": "",
      "bounds": "[559,2722][721,2866]",
      "center": [
        640,
        2794
      ],
      "long-clickable": false,
      "scroll_index": 0
    },
    {
      "class": "android.view.View",
      "text": "",
      "resource-id": "",
      "content-desc": "",
      "bounds": "[829,2722][991,2866]",
      "center": [
        910,
        2794
      ],
      "long-clickable": false,
      "scroll_index": 0
    },
    {
      "class": "android.view.View",
      "text": "",
      "resource-id": "",
      "content-desc": "",
      "bounds": "[1098,2722][1260,2866]",
      "center": [
        1179,
        2794
      ],
      "long-clickable": false,
      "scroll_index": 0
    },
    {
      "class": "android.view.View",
      "text": "🍤",
      "resource-id": "",
      "content-desc": "",
      "bounds": "[60,121][1284,939]",
      "center": [
        672,
        530
      ],
      "long-clickable": false,
      "scroll_index": 1
    },
    {
      "class": "android.view.View",
      "text": "",
      "resource-id": "",
      "content-desc": "",
      "bounds": "[1122,139][1266,283]",
      "center": [
        1194,
        211
      ],
      "long-clickable": false,
      "scroll_index": 1
    },
    {
      "class": "android.view.View",
      "text": "🍝",
      "resource-id": "",
      "content-desc": "",
      "bounds": "[60,999][1284,1817]",
      "center": [
        672,
        1408
      ],
      "long-clickable": false,
      "scroll_index": 1
    },
    {
      "class": "android.view.View",
      "text": "",
      "resource-id": "",
      "content-desc": "",
      "bounds": "[1122,1017][1266,1161]",
      "center": [
        1194,
        1089
      ],
      "long-clickable": false,
      "scroll_index": 1
    },
    {
      "class": "android.view.View",
      "text": "🧈",
      "resource-id": "",
      "content-desc": "",
      "bounds": "[60,1877][1284,2740]",
      "center": [
        672,
        2308
      ],
      "long-clickable": false,
      "scroll_index": 1
    },
    {
      "class": "android.view.View",
      "text": "",
      "resource-id": "",
      "content-desc": "",
      "bounds": "[1122,1895][1266,2039]",
      "center": [
        1194,
        1967
      ],
      "long-clickable": false,
      "scroll_index": 1
    },
    {
      "class": "android.view.View",
      "text": "🍝",
      "resource-id": "",
      "content-desc": "",
      "bounds": "[60,87][1284,870]",
      "center": [
        672,
        478
      ],
      "long-clickable": false,
      "scroll_index": 2
    },
    {
      "class": "android.view.View",
      "text": "",
      "resource-id": "",
      "content-desc": "",
      "bounds": "[1122,87][1266,214]",
      "center": [
        1194,
        150
      ],
      "long-clickable": false,
      "scroll_index": 2
    },
    {
      "class": "android.view.View",
      "text": "🧈",
      "resource-id": "",
      "content-desc": "",
      "bounds": "[60,930][1284,1811]",
      "center": [
        672,
        1370
      ],
      "long-clickable": false,
      "scroll_index": 2
    },
    {
      "class": "android.view.View",
      "text": "",
      "resource-id": "",
      "content-desc": "",
      "bounds": "[1122,948][1266,1092]",
      "center": [
        1194,
        1020
      ],
      "long-clickable": false,
      "scroll_index": 2
    },
    {
      "class": "android.view.View",
      "text": "🍫",
      "resource-id": "",
      "content-desc": "",
      "bounds": "[60,1871][1284,2689]",
      "center": [
        672,
        2280
      ],
      "long-clickable": false,
      "scroll_index": 2
    },
    {
      "class": "android.view.View",
      "text": "",
      "resource-id": "",
      "content-desc": "",
      "bounds": "[1122,1889][1266,2033]",
      "center": [
        1194,
        1961
      ],
      "long-clickable": false,
      "scroll_index": 2
    },
    {
      "class": "android.view.View",
      "text": "🧈",
      "resource-id": "",
      "content-desc": "",
      "bounds": "[60,87][1284,948]",
      "center": [
        672,
        517
      ],
      "long-clickable": false,
      "scroll_index": 3
    },
    {
      "class": "android.view.View",
      "text": "",
      "resource-id": "",
      "content-desc": "",
      "bounds": "[1122,87][1266,229]",
      "center": [
        1194,
        158
      ],
      "long-clickable": false,
      "scroll_index": 3
    },
    {
      "class": "android.view.View",
      "text": "🍫",
      "resource-id": "",
      "content-desc": "",
      "bounds": "[60,1008][1284,1826]",
      "center": [
        672,
        1417
      ],
      "long-clickable": false,
      "scroll_index": 3
    },
    {
      "class": "android.view.View",
      "text": "",
      "resource-id": "",
      "content-desc": "",
      "bounds": "[1122,1026][1266,1170]",
      "center": [
        1194,
        1098
      ],
      "long-clickable": false,
      "scroll_index": 3
    },
    {
      "class": "android.view.View",
      "text": "🫓",
      "resource-id": "",
      "content-desc": "",
      "bounds": "[60,1886][1284,2704]",
      "center": [
        672,
        2295
      ],
      "long-clickable": false,
      "scroll_index": 3
    },
    {
      "class": "android.view.View",
      "text": "",
      "resource-id": "",
      "content-desc": "",
      "bounds": "[1122,1904][1266,2048]",
      "center": [
        1194,
        1976
      ],
      "long-clickable": false,
      "scroll_index": 3
    },
    {
      "class": "android.view.View",
      "text": "",
      "resource-id": "",
      "content-desc": "",
      "bounds": "[60,87][1284,119]",
      "center": [
        672,
        103
      ],
      "long-clickable": false,
      "scroll_index": 4
    },
    {
      "class": "android.view.View",
      "text": "🍫",
      "resource-id": "",
      "content-desc": "",
      "bounds": "[60,179][1284,997]",
      "center": [
        672,
        588
      ],
      "long-clickable": false,
      "scroll_index": 4
    },
    {
      "class": "android.view.View",
      "text": "",
      "resource-id": "",
      "content-desc": "",
      "bounds": "[1122,197][1266,341]",
      "center": [
        1194,
        269
      ],
      "long-clickable": false,
      "scroll_index": 4
    },
    {
      "class": "android.view.View",
      "text": "🫓",
      "resource-id": "",
      "content-desc": "",
      "bounds": "[60,1057][1284,1875]",
      "center": [
        672,
        1466
      ],
      "long-clickable": false,
      "scroll_index": 4
    },
    {
      "class": "android.view.View",
      "text": "",
      "resource-id": "",
      "content-desc": "",
      "bounds": "[1122,1075][1266,1219]",
      "center": [
        1194,
        1147
      ],
      "long-clickable": false,
      "scroll_index": 4
    },
    {
      "class": "android.view.View",
      "text": "🍎",
      "resource-id": "",
      "content-desc": "",
      "bounds": "[60,1935][1284,2740]",
      "center": [
        672,
        2337
      ],
      "long-clickable": false,
      "scroll_index": 4
    },
    {
      "class": "android.view.View",
      "text": "",
      "resource-id": "",
      "content-desc": "",
      "bounds": "[1122,1953][1266,2097]",
      "center": [
        1194,
        2025
      ],
      "long-clickable": false,
      "scroll_index": 4
    },
    {
      "class": "android.view.View",
      "text": "🫓",
      "resource-id": "",
      "content-desc": "",
      "bounds": "[60,94][1284,912]",
      "center": [
        672,
        503
      ],
      "long-clickable": false,
      "scroll_index": 5
    },
    {
      "class": "android.view.View",
      "text": "",
      "resource-id": "",
      "content-desc": "",
      "bounds": "[1122,112][1266,256]",
      "center": [
        1194,
        184
      ],
      "long-clickable": false,
      "scroll_index": 5
    },
    {
      "class": "android.view.View",
      "text": "🍎",
      "resource-id": "",
      "content-desc": "",
      "bounds": "[60,972][1284,1790]",
      "center": [
        672,
        1381
      ],
      "long-clickable": false,
      "scroll_index": 5
    },
    {
      "class": "android.view.View",
      "text": "",
      "resource-id": "",
      "content-desc": "",
      "bounds": "[1122,990][1266,1134]",
      "center": [
        1194,
        1062
      ],
      "long-clickable": false,
      "scroll_index": 5
    },
    {
      "class": "android.view.View",
      "text": "🥣",
      "resource-id": "",
      "content-desc": "",
      "bounds": "[60,1850][1284,2668]",
      "center": [
        672,
        2259
      ],
      "long-clickable": false,
      "scroll_index": 5
    },
    {
      "class": "android.view.View",
      "text": "",
      "resource-id": "",
      "content-desc": "",
      "bounds": "[1122,1868][1266,2012]",
      "center": [
        1194,
        1940
      ],
      "long-clickable": false,
      "scroll_index": 5
    },
    {
      "class": "android.view.View",
      "text": "🍎",
      "resource-id": "",
      "content-desc": "",
      "bounds": "[60,129][1284,947]",
      "center": [
        672,
        538
      ],
      "long-clickable": false,
      "scroll_index": 6
    },
    {
      "class": "android.view.View",
      "text": "",
      "resource-id": "",
      "content-desc": "",
      "bounds": "[1122,147][1266,291]",
      "center": [
        1194,
        219
      ],
      "long-clickable": false,
      "scroll_index": 6
    },
    {
      "class": "android.view.View",
      "text": "🥣",
      "resource-id": "",
      "content-desc": "",
      "bounds": "[60,1007][1284,1825]",
      "center": [
        672,
        1416
      ],
      "long-clickable": false,
      "scroll_index": 6
    },
    {
      "class": "android.view.View",
      "text": "",
      "resource-id": "",
      "content-desc": "",
      "bounds": "[1122,1025][1266,1169]",
      "center": [
        1194,
        1097
      ],
      "long-clickable": false,
      "scroll_index": 6
    },
    {
      "class": "android.view.View",
      "text": "🍋",
      "resource-id": "",
      "content-desc": "",
      "bounds": "[60,1885][1284,2703]",
      "center": [
        672,
        2294
      ],
      "long-clickable": false,
      "scroll_index": 6
    },
    {
      "class": "android.view.View",
      "text": "",
      "resource-id": "",
      "content-desc": "",
      "bounds": "[1122,1903][1266,2047]",
      "center": [
        1194,
        1975
      ],
      "long-clickable": false,
      "scroll_index": 6
    },
    {
      "class": "android.view.View",
      "text": "🥣",
      "resource-id": "",
      "content-desc": "",
      "bounds": "[60,87][1284,905]",
      "center": [
        672,
        496
      ],
      "long-clickable": false,
      "scroll_index": 7
    },
    {
      "class": "android.view.View",
      "text": "",
      "resource-id": "",
      "content-desc": "",
      "bounds": "[1122,105][1266,249]",
      "center": [
        1194,
        177
      ],
      "long-clickable": false,
      "scroll_index": 7
    },
    {
      "class": "android.view.View",
      "text": "🍋",
      "resource-id": "",
      "content-desc": "",
      "bounds": "[60,965][1284,1783]",
      "center": [
        672,
        1374
      ],
      "long-clickable": false,
      "scroll_index": 7
    },
    {
      "class": "android.view.View",
      "text": "",
      "resource-id": "",
      "content-desc": "",
      "bounds": "[1122,983][1266,1127]",
      "center": [
        1194,
        1055
      ],
      "long-clickable": false,
      "scroll_index": 7
    },
    {
      "class": "android.view.View",
      "text": "🥭",
      "resource-id": "",
      "content-desc": "",
      "bounds": "[60,1843][1284,2661]",
      "center": [
        672,
        2252
      ],
      "long-clickable": false,
      "scroll_index": 7
    },
    {
      "class": "android.view.View",
      "text": "",
      "resource-id": "",
      "content-desc": "",
      "bounds": "[1122,1861][1266,2005]",
      "center": [
        1194,
        1933
      ],
      "long-clickable": false,
      "scroll_index": 7
    },
    {
      "class": "android.view.View",
      "text": "🍋",
      "resource-id": "",
      "content-desc": "",
      "bounds": "[60,89][1284,907]",
      "center": [
        672,
        498
      ],
      "long-clickable": false,
      "scroll_index": 8
    },
    {
      "class": "android.view.View",
      "text": "",
      "resource-id": "",
      "content-desc": "",
      "bounds": "[1122,107][1266,251]",
      "center": [
        1194,
        179
      ],
      "long-clickable": false,
      "scroll_index": 8
    },
    {
      "class": "android.view.View",
      "text": "🥭",
      "resource-id": "",
      "content-desc": "",
      "bounds": "[60,967][1284,1785]",
      "center": [
        672,
        1376
      ],
      "long-clickable": false,
      "scroll_index": 8
    },
    {
      "class": "android.view.View",
      "text": "",
      "resource-id": "",
      "content-desc": "",
      "bounds": "[1122,985][1266,1129]",
      "center": [
        1194,
        1057
      ],
      "long-clickable": false,
      "scroll_index": 8
    },
    {
      "class": "android.view.View",
      "text": "🍕",
      "resource-id": "",
      "content-desc": "",
      "bounds": "[60,1845][1284,2663]",
      "center": [
        672,
        2254
      ],
      "long-clickable": false,
      "scroll_index": 8
    },
    {
      "class": "android.view.View",
      "text": "",
      "resource-id": "",
      "content-desc": "",
      "bounds": "[1122,1863][1266,2007]",
      "center": [
        1194,
        1935
      ],
      "long-clickable": false,
      "scroll_index": 8
    },
    {
      "class": "android.view.View",
      "text": "🍋",
      "resource-id": "",
      "content-desc": "",
      "bounds": "[60,87][1284,828]",
      "center": [
        672,
        457
      ],
      "long-clickable": false,
      "scroll_index": 9
    },
    {
      "class": "android.view.View",
      "text": "",
      "resource-id": "",
      "content-desc": "",
      "bounds": "[1122,87][1266,172]",
      "center": [
        1194,
        129
      ],
      "long-clickable": false,
      "scroll_index": 9
    },
    {
      "class": "android.view.View",
      "text": "🥭",
      "resource-id": "",
      "content-desc": "",
      "bounds": "[60,888][1284,1706]",
      "center": [
        672,
        1297
      ],
      "long-clickable": false,
      "scroll_index": 9
    },
    {
      "class": "android.view.View",
      "text": "",
      "resource-id": "",
      "content-desc": "",
      "bounds": "[1122,906][1266,1050]",
      "center": [
        1194,
        978
      ],
      "long-clickable": false,
      "scroll_index": 9
    },
    {
      "class": "android.view.View",
      "text": "🍕",
      "resource-id": "",
      "content-desc": "",
      "bounds": "[60,1766][1284,2584]",
      "center": [
        672,
        2175
      ],
      "long-clickable": false,
      "scroll_index": 9
    },
    {
      "class": "android.view.View",
      "text": "",
      "resource-id": "",
      "content-desc": "",
      "bounds": "[1122,1784][1266,1928]",
      "center": [
        1194,
        1856
      ],
      "long-clickable": false,
      "scroll_index": 9
    }
  ],
  "scroll_container_bounds": [
    0,
    159,
    1344,
    2668
  ],
  "screenshot": "page_0035_MainActivity/screenshot.png",
  "view_xml": "page_0035_MainActivity/view.xml",
  "screenshots": [
    "page_0035_MainActivity/screenshot.png",
    "page_0035_MainActivity/screenshot_scroll_1.png",
    "page_0035_MainActivity/screenshot_scroll_2.png",
    "page_0035_MainActivity/screenshot_scroll_3.png",
    "page_0035_MainActivity/screenshot_scroll_4.png",
    "page_0035_MainActivity/screenshot_scroll_5.png",
    "page_0035_MainActivity/screenshot_scroll_6.png",
    "page_0035_MainActivity/screenshot_scroll_7.png",
    "page_0035_MainActivity/screenshot_scroll_8.png",
    "page_0035_MainActivity/screenshot_scroll_9.png"
  ],
  "view_xmls": [
    "page_0035_MainActivity/view.xml",
    "page_0035_MainActivity/view_scroll_1.xml",
    "page_0035_MainActivity/view_scroll_2.xml",
    "page_0035_MainActivity/view_scroll_3.xml",
    "page_0035_MainActivity/view_scroll_4.xml",
    "page_0035_MainActivity/view_scroll_5.xml",
    "page_0035_MainActivity/view_scroll_6.xml",
    "page_0035_MainActivity/view_scroll_7.xml",
    "page_0035_MainActivity/view_scroll_8.xml",
    "page_0035_MainActivity/view_scroll_9.xml"
  ],
  "came_from": "根页面",
  "trigger_element": "unknown",
  "click_path": [
    {
      "from": "根页面",
      "element": "unknown",
      "center": [
        672,
        101
      ],
      "resource-id": "",
      "text": "",
      "content-desc": "",
      "long-clickable": false,
      "scroll_info": {
        "scroll_index": 8,
        "container_bounds": [
          0,
          159,
          1344,
          2668
        ]
      }
    }
  ]
}