{"attributes":{"accessibilityId":"","backgroundColor":"","backgroundImage":"","blur":"","bounds":"[0,0][1280,2832]","checkable":"","checked":"","clickable":"","clip":"","description":"","displayId":"","enabled":"","focused":"","hitTestBehavior":"","hostWindowId":"","id":"","key":"","longClickable":"","opacity":"","origBounds":"","originalText":"","scrollable":"","selected":"","text":"","type":"","zIndex":""},"children":[{"attributes":{"abilityName":"EntryAbility","accessibilityId":"0","backgroundColor":"#00000000","backgroundImage":"empty source","blur":"","bounds":"[0,137][1280,2832]","bundleName":"com.example.antennapodharmony","checkable":"false","checked":"false","clickable":"false","clip":"false","description":"","displayId":"0","enabled":"true","focused":"true","hashcode":"33:0","hierarchy":"ROOT33","hint":"","hitTestBehavior":"HitTestMode.Default","hostWindowId":"33","id":"","key":"","longClickable":"false","opacity":"1.000000","origBounds":"[0,0][1280,2832]","originalText":"","pagePath":"pages/Index","scrollable":"false","selected":"false","text":"","type":"root","visible":"true","zIndex":"0"},"children":[{"attributes":{"accessibilityId":"4","backgroundColor":"#00000000","backgroundImage":"empty source","blur":"","bounds":"[0,137][1280,2734]","checkable":"false","checked":"false","clickable":"false","clip":"false","description":"","displayId":"0","enabled":"true","focused":"true","hashcode":"33:4","hierarchy":"ROOT33,0","hint":"","hitTestBehavior":"HitTestMode.Default","hostWindowId":"33","id":"","key":"","longClickable":"false","opacity":"1.000000","origBounds":"[0,136][1280,2734]","originalText":"","scrollable":"false","selected":"false","text":"","type":"Column","visible":"true","zIndex":"0"},"children":[{"attributes":{"accessibilityId":"5","backgroundColor":"#FFF9FCFF","backgroundImage":"empty source","blur":"","bounds":"[0,137][1280,332]","checkable":"false","checked":"false","clickable":"false","clip":"false","description":"","displayId":"0","enabled":"true","focused":"false","hashcode":"33:5","hierarchy":"ROOT33,0,0","hint":"","hitTestBehavior":"HitTestMode.Default","hostWindowId":"33","id":"","key":"","longClickable":"false","opacity":"1.000000","origBounds":"[0,136][1280,332]","originalText":"","scrollable":"false","selected":"false","text":"","type":"Row","visible":"true","zIndex":"0"},"children":[{"attributes":{"accessibilityId":"6","backgroundColor":"#00000000","backgroundImage":"empty source","blur":"","bounds":"[56,193][1028,275]","checkable":"false","checked":"false","clickable":"false","clip":"false","description":"","displayId":"0","enabled":"true","focused":"false","hashcode":"33:6","hierarchy":"ROOT33,0,0,0","hint":"","hitTestBehavior":"HitTestMode.Default","hostWindowId":"33","id":"","key":"","longClickable":"false","opacity":"1.000000","origBounds":"[56,193][1028,275]","originalText":"Home","scrollable":"false","selected":"false","text":"Home","type":"Text","visible":"true","zIndex":"0"},"children":[]},{"attributes":{"accessibilityId":"7","backgroundColor":"#00000000","backgroundImage":"empty source","blur":"","bounds":"[1028,192][1112,276]","checkable":"false","checked":"false","clickable":"true","clip":"false","description":"","displayId":"0","enabled":"true","focused":"false","hashcode":"33:7","hierarchy":"ROOT33,0,0,1","hint":"","hitTestBehavior":"HitTestMode.Default","hostWindowId":"33","id":"","key":"","longClickable":"false","opacity":"1.000000","origBounds":"[1028,192][1112,276]","originalText":"","scrollable":"false","selected":"false","text":"","type":"Image","visible":"true","zIndex":"0"},"children":[]},{"attributes":{"accessibilityId":"8","backgroundColor":"#00000000","backgroundImage":"empty source","blur":"","bounds":"[1168,192][1252,276]","checkable":"false","checked":"false","clickable":"true","clip":"false","description":"","displayId":"0","enabled":"true","focused":"false","hashcode":"33:8","hierarchy":"ROOT33,0,0,2","hint":"","hitTestBehavior":"HitTestMode.Default","hostWindowId":"33","id":"","key":"","longClickable":"false","opacity":"1.000000","origBounds":"[1168,192][1252,276]","originalText":"","scrollable":"false","selected":"false","text":"","type":"Image","visible":"true","zIndex":"0"},"children":[]}]},{"attributes":{"accessibilityId":"9","backgroundColor":"#FFF9FCFF","backgroundImage":"empty source","blur":"","bounds":"[0,332][1280,2510]","checkable":"false","checked":"false","clickable":"false","clip":"false","description":"","displayId":"0","enabled":"true","focused":"false","hashcode":"33:9","hierarchy":"ROOT33,0,1","hint":"","hitTestBehavior":"HitTestMode.Default","hostWindowId":"33","id":"","key":"","longClickable":"false","opacity":"1.000000","origBounds":"[0,332][1280,2510]","originalText":"","scrollable":"false","selected":"false","text":"","type":"Column","visible":"true","zIndex":"0"},"children":[{"attributes":{"accessibilityId":"12","backgroundColor":"#00000000","backgroundImage":"empty source","blur":"","bounds":"[0,332][1280,2510]","checkable":"false","checked":"false","clickable":"false","clip":"false","description":"","displayId":"0","enabled":"true","focused":"false","hashcode":"33:12","hierarchy":"ROOT33,0,1,0","hint":"","hitTestBehavior":"HitTestMode.Default","hostWindowId":"33","id":"","key":"","longClickable":"false","opacity":"1.000000","origBounds":"[0,332][1280,2510]","originalText":"","scrollable":"false","selected":"false","text":"","type":"Stack","visible":"true","zIndex":"0"},"children":[{"attributes":{"accessibilityId":"13","backgroundColor":"#00000000","backgroundImage":"empty source","blur":"","bounds":"[0,332][1280,2510]","checkable":"false","checked":"false","clickable":"false","clip":"false","description":"","displayId":"0","enabled":"true","focused":"false","hashcode":"33:13","hierarchy":"ROOT33,0,1,0,0","hint":"","hitTestBehavior":"HitTestMode.Default","hostWindowId":"33","id":"","key":"","longClickable":"false","opacity":"1.000000","origBounds":"[0,332][1280,2510]","originalText":"","scrollable":"false","selected":"false","text":"","type":"Column","visible":"true","zIndex":"0"},"children":[{"attributes":{"accessibilityId":"14","backgroundColor":"#00000000","backgroundImage":"empty source","blur":"","bounds":"[528,500][752,724]","checkable":"false","checked":"false","clickable":"false","clip":"false","description":"","displayId":"0","enabled":"true","focused":"false","hashcode":"33:14","hierarchy":"ROOT33,0,1,0,0,0","hint":"","hitTestBehavior":"HitTestMode.Default","hostWindowId":"33","id":"","key":"","longClickable":"false","opacity":"1.000000","origBounds":"[528,500][752,724]","originalText":"","scrollable":"false","selected":"false","text":"","type":"Image","visible":"true","zIndex":"0"},"children":[]},{"attributes":{"accessibilityId":"15","backgroundColor":"#00000000","backgroundImage":"empty source","blur":"","bounds":"[112,780][1168,862]","checkable":"false","checked":"false","clickable":"false","clip":"false","description":"","displayId":"0","enabled":"true","focused":"false","hashcode":"33:15","hierarchy":"ROOT33,0,1,0,0,1","hint":"","hitTestBehavior":"HitTestMode.Default","hostWindowId":"33","id":"","key":"","longClickable":"false","opacity":"1.000000","origBounds":"[112,780][1168,862]","originalText":"Welcome to AntennaPod!","scrollable":"false","selected":"false","text":"Welcome to AntennaPod!","type":"Text","visible":"true","zIndex":"0"},"children":[]},{"attributes":{"accessibilityId":"16","backgroundColor":"#00000000","backgroundImage":"empty source","blur":"","bounds":"[112,890][1168,1004]","checkable":"false","checked":"false","clickable":"false","clip":"false","description":"","displayId":"0","enabled":"true","focused":"false","hashcode":"33:16","hierarchy":"ROOT33,0,1,0,0,2","hint":"","hitTestBehavior":"HitTestMode.Default","hostWindowId":"33","id":"","key":"","longClickable":"false","opacity":"1.000000","origBounds":"[112,890][1168,1004]","originalText":"You are not subscribed to any podcasts yet. Open the menu to add a podcast.","scrollable":"false","selected":"false","text":"You are not subscribed to any podcasts yet. Open the menu to add a podcast.","type":"Text","visible":"true","zIndex":"0"},"children":[]}]},{"attributes":{"accessibilityId":"17","backgroundColor":"#00000000","backgroundImage":"empty source","blur":"","bounds":"[944,2174][1224,2454]","checkable":"false","checked":"false","clickable":"false","clip":"false","description":"","displayId":"0","enabled":"true","focused":"false","hashcode":"33:17","hierarchy":"ROOT33,0,1,0,1","hint":"","hitTestBehavior":"HitTestMode.Default","hostWindowId":"33","id":"","key":"","longClickable":"false","opacity":"1.000000","origBounds":"[944,2174][1224,2454]","originalText":"","scrollable":"false","selected":"false","text":"","type":"Image","visible":"true","zIndex":"0"},"children":[]}]}]},{"attributes":{"accessibilityId":"19","backgroundColor":"#FFEFEEEE","backgroundImage":"empty source","blur":"","bounds":"[0,2510][1280,2734]","checkable":"false","checked":"false","clickable":"false","clip":"false","description":"","displayId":"0","enabled":"true","focused":"false","hashcode":"33:19","hierarchy":"ROOT33,0,2","hint":"","hitTestBehavior":"HitTestMode.Default","hostWindowId":"33","id":"","key":"","longClickable":"false","opacity":"1.000000","origBounds":"[0,2510][1280,2734]","originalText":"","scrollable":"false","selected":"false","text":"","type":"Row","visible":"true","zIndex":"0"},"children":[{"attributes":{"accessibilityId":"20","backgroundColor":"#00000000","backgroundImage":"empty source","blur":"","bounds":"[0,2510][256,2734]","checkable":"false","checked":"false","clickable":"true","clip":"false","description":"","displayId":"0","enabled":"true","focused":"false","hashcode":"33:20","hierarchy":"ROOT33,0,2,0","hint":"","hitTestBehavior":"HitTestMode.Default","hostWindowId":"33","id":"","key":"","longClickable":"false","opacity":"1.000000","origBounds":"[0,2510][256,2734]","originalText":"","scrollable":"false","selected":"false","text":"","type":"Column","visible":"true","zIndex":"0"},"children":[{"attributes":{"accessibilityId":"21","backgroundColor":"#00000000","backgroundImage":"empty source","blur":"","bounds":"[86,2549][170,2633]","checkable":"false","checked":"false","clickable":"false","clip":"false","description":"","displayId":"0","enabled":"true","focused":"false","hashcode":"33:21","hierarchy":"ROOT33,0,2,0,0","hint":"","hitTestBehavior":"HitTestMode.Default","hostWindowId":"33","id":"","key":"","longClickable":"false","opacity":"1.000000","origBounds":"[86,2549][170,2633]","originalText":"","scrollable":"false","selected":"false","text":"","type":"Image","visible":"true","zIndex":"0"},"children":[]},{"attributes":{"accessibilityId":"22","backgroundColor":"#00000000","backgroundImage":"empty source","blur":"","bounds":"[71,2647][186,2696]","checkable":"false","checked":"false","clickable":"false","clip":"false","description":"","displayId":"0","enabled":"true","focused":"false","hashcode":"33:22","hierarchy":"ROOT33,0,2,0,1","hint":"","hitTestBehavior":"HitTestMode.Default","hostWindowId":"33","id":"","key":"","longClickable":"false","opacity":"1.000000","origBounds":"[71,2647][186,2696]","originalText":"Home","scrollable":"false","selected":"false","text":"Home","type":"Text","visible":"true","zIndex":"0"},"children":[]}]},{"attributes":{"accessibilityId":"23","backgroundColor":"#00000000","backgroundImage":"empty source","blur":"","bounds":"[256,2510][512,2734]","checkable":"false","checked":"false","clickable":"true","clip":"false","description":"","displayId":"0","enabled":"true","focused":"false","hashcode":"33:23","hierarchy":"ROOT33,0,2,1","hint":"","hitTestBehavior":"HitTestMode.Default","hostWindowId":"33","id":"","key":"","longClickable":"false","opacity":"1.000000","origBounds":"[256,2510][512,2734]","originalText":"","scrollable":"false","selected":"false","text":"","type":"Column","visible":"true","zIndex":"0"},"children":[{"attributes":{"accessibilityId":"24","backgroundColor":"#00000000","backgroundImage":"empty source","blur":"","bounds":"[342,2549][426,2633]","checkable":"false","checked":"false","clickable":"false","clip":"false","description":"","displayId":"0","enabled":"true","focused":"false","hashcode":"33:24","hierarchy":"ROOT33,0,2,1,0","hint":"","hitTestBehavior":"HitTestMode.Default","hostWindowId":"33","id":"","key":"","longClickable":"false","opacity":"1.000000","origBounds":"[342,2549][426,2633]","originalText":"","scrollable":"false","selected":"false","text":"","type":"Image","visible":"true","zIndex":"0"},"children":[]},{"attributes":{"accessibilityId":"25","backgroundColor":"#00000000","backgroundImage":"empty source","blur":"","bounds":"[321,2647][448,2696]","checkable":"false","checked":"false","clickable":"false","clip":"false","description":"","displayId":"0","enabled":"true","focused":"false","hashcode":"33:25","hierarchy":"ROOT33,0,2,1,1","hint":"","hitTestBehavior":"HitTestMode.Default","hostWindowId":"33","id":"","key":"","longClickable":"false","opacity":"1.000000","origBounds":"[321,2647][448,2696]","originalText":"Queue","scrollable":"false","selected":"false","text":"Queue","type":"Text","visible":"true","zIndex":"0"},"children":[]}]},{"attributes":{"accessibilityId":"26","backgroundColor":"#00000000","backgroundImage":"empty source","blur":"","bounds":"[512,2510][768,2734]","checkable":"false","checked":"false","clickable":"true","clip":"false","description":"","displayId":"0","enabled":"true","focused":"false","hashcode":"33:26","hierarchy":"ROOT33,0,2,2","hint":"","hitTestBehavior":"HitTestMode.Default","hostWindowId":"33","id":"","key":"","longClickable":"false","opacity":"1.000000","origBounds":"[512,2510][768,2734]","originalText":"","scrollable":"false","selected":"false","text":"","type":"Column","visible":"true","zIndex":"0"},"children":[{"attributes":{"accessibilityId":"27","backgroundColor":"#00000000","backgroundImage":"empty source","blur":"","bounds":"[598,2549][682,2633]","checkable":"false","checked":"false","clickable":"false","clip":"false","description":"","displayId":"0","enabled":"true","focused":"false","hashcode":"33:27","hierarchy":"ROOT33,0,2,2,0","hint":"","hitTestBehavior":"HitTestMode.Default","hostWindowId":"33","id":"","key":"","longClickable":"false","opacity":"1.000000","origBounds":"[598,2549][682,2633]","originalText":"","scrollable":"false","selected":"false","text":"","type":"Image","visible":"true","zIndex":"0"},"children":[]},{"attributes":{"accessibilityId":"28","backgroundColor":"#00000000","backgroundImage":"empty source","blur":"","bounds":"[587,2647][693,2696]","checkable":"false","checked":"false","clickable":"false","clip":"false","description":"","displayId":"0","enabled":"true","focused":"false","hashcode":"33:28","hierarchy":"ROOT33,0,2,2,1","hint":"","hitTestBehavior":"HitTestMode.Default","hostWindowId":"33","id":"","key":"","longClickable":"false","opacity":"1.000000","origBounds":"[587,2647][693,2696]","originalText":"Inbox","scrollable":"false","selected":"false","text":"Inbox","type":"Text","visible":"true","zIndex":"0"},"children":[]}]},{"attributes":{"accessibilityId":"29","backgroundColor":"#00000000","backgroundImage":"empty source","blur":"","bounds":"[768,2510][1024,2734]","checkable":"false","checked":"false","clickable":"true","clip":"false","description":"","displayId":"0","enabled":"true","focused":"false","hashcode":"33:29","hierarchy":"ROOT33,0,2,3","hint":"","hitTestBehavior":"HitTestMode.Default","hostWindowId":"33","id":"","key":"","longClickable":"false","opacity":"1.000000","origBounds":"[768,2510][1024,2734]","originalText":"","scrollable":"false","selected":"false","text":"","type":"Column","visible":"true","zIndex":"0"},"children":[{"attributes":{"accessibilityId":"30","backgroundColor":"#00000000","backgroundImage":"empty source","blur":"","bounds":"[854,2524][938,2608]","checkable":"false","checked":"false","clickable":"false","clip":"false","description":"","displayId":"0","enabled":"true","focused":"false","hashcode":"33:30","hierarchy":"ROOT33,0,2,3,0","hint":"","hitTestBehavior":"HitTestMode.Default","hostWindowId":"33","id":"","key":"","longClickable":"false","opacity":"1.000000","origBounds":"[854,2524][938,2608]","originalText":"","scrollable":"false","selected":"false","text":"","type":"Image","visible":"true","zIndex":"0"},"children":[]},{"attributes":{"accessibilityId":"31","backgroundColor":"#00000000","backgroundImage":"empty source","blur":"","bounds":"[776,2622][1016,2720]","checkable":"false","checked":"false","clickable":"false","clip":"false","description":"","displayId":"0","enabled":"true","focused":"false","hashcode":"33:31","hierarchy":"ROOT33,0,2,3,1","hint":"","hitTestBehavior":"HitTestMode.Default","hostWindowId":"33","id":"","key":"","longClickable":"false","opacity":"1.000000","origBounds":"[776,2622][1016,2720]","originalText":"Subscriptions","scrollable":"false","selected":"false","text":"Subscriptions","type":"Text","visible":"true","zIndex":"0"},"children":[]}]},{"attributes":{"accessibilityId":"32","backgroundColor":"#00000000","backgroundImage":"empty source","blur":"","bounds":"[1024,2510][1280,2734]","checkable":"false","checked":"false","clickable":"true","clip":"false","description":"","displayId":"0","enabled":"true","focused":"false","hashcode":"33:32","hierarchy":"ROOT33,0,2,4","hint":"","hitTestBehavior":"HitTestMode.Default","hostWindowId":"33","id":"","key":"","longClickable":"false","opacity":"1.000000","origBounds":"[1024,2510][1280,2734]","originalText":"","scrollable":"false","selected":"false","text":"","type":"Column","visible":"true","zIndex":"0"},"children":[{"attributes":{"accessibilityId":"33","backgroundColor":"#00000000","backgroundImage":"empty source","blur":"","bounds":"[1110,2549][1194,2633]","checkable":"false","checked":"false","clickable":"false","clip":"false","description":"","displayId":"0","enabled":"true","focused":"false","hashcode":"33:33","hierarchy":"ROOT33,0,2,4,0","hint":"","hitTestBehavior":"HitTestMode.Default","hostWindowId":"33","id":"","key":"","longClickable":"false","opacity":"1.000000","origBounds":"[1110,2549][1194,2633]","originalText":"","scrollable":"false","selected":"false","text":"","type":"Image","visible":"true","zIndex":"0"},"children":[]},{"attributes":{"accessibilityId":"34","backgroundColor":"#00000000","backgroundImage":"empty source","blur":"","bounds":"[1103,2647][1202,2696]","checkable":"false","checked":"false","clickable":"false","clip":"false","description":"","displayId":"0","enabled":"true","focused":"false","hashcode":"33:34","hierarchy":"ROOT33,0,2,4,1","hint":"","hitTestBehavior":"HitTestMode.Default","hostWindowId":"33","id":"","key":"","longClickable":"false","opacity":"1.000000","origBounds":"[1103,2647][1202,2696]","originalText":"More","scrollable":"false","selected":"false","text":"More","type":"Text","visible":"true","zIndex":"0"},"children":[]}]}]}]}]},{"attributes":{"abilityName":"","accessibilityId":"599","backgroundColor":"#00000000","backgroundImage":"empty source","blur":"","bounds":"[0,0][1280,136]","bundleName":"com.ohos.sceneboard","checkable":"false","checked":"false","clickable":"false","clip":"false","description":"","displayId":"0","enabled":"true","focused":"false","hashcode":"1:599","hierarchy":"ROOT21","hint":"","hitTestBehavior":"HitTestMode.None","hostWindowId":"21","id":"session21","key":"session21","longClickable":"false","opacity":"1.000000","origBounds":"[0,0][1280,136]","originalText":"","pagePath":"","scrollable":"false","selected":"false","text":"","type":"WindowScene","visible":"true","zIndex":"0"},"children":[{"attributes":{"accessibilityId":"600","backgroundColor":"#00000000","backgroundImage":"empty source","blur":"","bounds":"[0,0][1280,136]","checkable":"false","checked":"false","clickable":"false","clip":"false","description":"","displayId":"0","enabled":"true","focused":"false","hashcode":"1:600","hierarchy":"ROOT21,0","hint":"","hitTestBehavior":"HitTestMode.Default","hostWindowId":"21","id":"StatusBarBox","key":"StatusBarBox","longClickable":"false","opacity":"1.000000","origBounds":"[0,0][1280,136]","originalText":"","scrollable":"false","selected":"false","text":"","type":"__Common__","visible":"true","zIndex":"0"},"children":[{"attributes":{"accessibilityId":"910","backgroundColor":"#00000000","backgroundImage":"empty source","blur":"","bounds":"[0,0][1280,136]","checkable":"false","checked":"false","clickable":"false","clip":"false","description":"","displayId":"0","enabled":"true","focused":"false","hashcode":"1:910","hierarchy":"ROOT21,0,0","hint":"","hitTestBehavior":"HitTestMode.Default","hostWindowId":"21","id":"","key":"","longClickable":"false","opacity":"1.000000","origBounds":"[0,0][1280,136]","originalText":"","scrollable":"false","selected":"false","text":"","type":"Stack","visible":"true","zIndex":"0"},"children":[{"attributes":{"accessibilityId":"914","backgroundColor":"#00000000","backgroundImage":"empty source","blur":"","bounds":"[0,0][1280,136]","checkable":"false","checked":"false","clickable":"true","clip":"false","description":"","displayId":"0","enabled":"true","focused":"false","hashcode":"1:914","hierarchy":"ROOT21,0,0,0","hint":"","hitTestBehavior":"HitTestMode.Default","hostWindowId":"21","id":"StatusBarBridgeView","key":"StatusBarBridgeView","longClickable":"false","opacity":"1.000000","origBounds":"[0,0][1280,136]","originalText":"","scrollable":"false","selected":"false","text":"","type":"__Common__","visible":"true","zIndex":"0"},"children":[{"attributes":{"accessibilityId":"916","backgroundColor":"#00000000","backgroundImage":"empty source","blur":"","bounds":"[0,0][1280,136]","checkable":"false","checked":"false","clickable":"false","clip":"false","description":"","displayId":"0","enabled":"true","focused":"false","hashcode":"1:916","hierarchy":"ROOT21,0,0,0,0","hint":"","hitTestBehavior":"HitTestMode.Default","hostWindowId":"21","id":"","key":"","longClickable":"false","opacity":"1.000000","origBounds":"[0,0][1280,136]","originalText":"","scrollable":"false","selected":"false","text":"","type":"Stack","visible":"true","zIndex":"0"},"children":[{"attributes":{"accessibilityId":"917","backgroundColor":"#00000000","backgroundImage":"empty source","blur":"","bounds":"[53,38][192,122]","checkable":"false","checked":"false","clickable":"false","clip":"false","description":"","displayId":"0","enabled":"true","focused":"false","hashcode":"1:917","hierarchy":"ROOT21,0,0,0,0,0","hint":"","hitTestBehavior":"HitTestMode.Default","hostWindowId":"21","id":"status_bar_left_color_picker","key":"status_bar_left_color_picker","longClickable":"false","opacity":"1.000000","origBounds":"[53,38][192,122]","originalText":"","scrollable":"false","selected":"false","text":"","type":"Row","visible":"true","zIndex":"0"},"children":[]},{"attributes":{"accessibilityId":"918","backgroundColor":"#00000000","backgroundImage":"empty source","blur":"","bounds":"[952,38][1228,122]","checkable":"false","checked":"false","clickable":"false","clip":"false","description":"","displayId":"0","enabled":"true","focused":"false","hashcode":"1:918","hierarchy":"ROOT21,0,0,0,0,1","hint":"","hitTestBehavior":"HitTestMode.Default","hostWindowId":"21","id":"status_bar_right_color_picker","key":"status_bar_right_color_picker","longClickable":"false","opacity":"1.000000","origBounds":"[952,38][1228,122]","originalText":"","scrollable":"false","selected":"false","text":"","type":"Row","visible":"true","zIndex":"0"},"children":[]},{"attributes":{"accessibilityId":"919","backgroundColor":"#00000000","backgroundImage":"empty source","blur":"","bounds":"[53,38][1228,122]","checkable":"false","checked":"false","clickable":"false","clip":"false","description":"","displayId":"0","enabled":"true","focused":"false","hashcode":"1:919","hierarchy":"ROOT21,0,0,0,0,2","hint":"","hitTestBehavior":"HitTestMode.Default","hostWindowId":"21","id":"status_bar_color_picker","key":"status_bar_color_picker","longClickable":"false","opacity":"1.000000","origBounds":"[53,38][1228,122]","originalText":"","scrollable":"false","selected":"false","text":"","type":"Row","visible":"true","zIndex":"0"},"children":[]},{"attributes":{"accessibilityId":"920","backgroundColor":"#00000000","backgroundImage":"empty source","blur":"0.00px","bounds":"[0,0][1280,136]","checkable":"false","checked":"false","clickable":"false","clip":"false","description":"","displayId":"0","enabled":"true","focused":"false","hashcode":"1:920","hierarchy":"ROOT21,0,0,0,0,3","hint":"","hitTestBehavior":"HitTestMode.Default","hostWindowId":"21","id":"StatusBarView","key":"StatusBarView","longClickable":"false","opacity":"1.000000","origBounds":"[0,0][1280,136]","originalText":"","scrollable":"false","selected":"false","text":"","type":"Stack","visible":"true","zIndex":"0"},"children":[{"attributes":{"accessibilityId":"976","backgroundColor":"#00FFFFFF","backgroundImage":"empty source","blur":"","bounds":"[0,0][1280,136]","checkable":"false","checked":"false","clickable":"false","clip":"false","description":"","displayId":"0","enabled":"true","focused":"false","hashcode":"1:976","hierarchy":"ROOT21,0,0,0,0,3,0","hint":"","hitTestBehavior":"HitTestMode.Default","hostWindowId":"21","id":"StatusBarBackground_Row_0","key":"StatusBarBackground_Row_0","longClickable":"false","opacity":"1.000000","origBounds":"[0,0][1280,137]","originalText":"","scrollable":"false","selected":"false","text":"","type":"Row","visible":"true","zIndex":"0"},"children":[]},{"attributes":{"accessibilityId":"926","backgroundColor":"#00000000","backgroundImage":"empty source","blur":"","bounds":"[53,38][1280,122]","checkable":"false","checked":"false","clickable":"false","clip":"false","description":"","displayId":"0","enabled":"true","focused":"false","hashcode":"1:926","hierarchy":"ROOT21,0,0,0,0,3,1","hint":"","hitTestBehavior":"HitTestMode.Default","hostWindowId":"21","id":"sbg_left","key":"sbg_left","longClickable":"false","opacity":"1.000000","origBounds":"[53,38][1333,122]","originalText":"","scrollable":"false","selected":"false","text":"","type":"Stack","visible":"true","zIndex":"0"},"children":[{"attributes":{"accessibilityId":"927","backgroundColor":"#00000000","backgroundImage":"empty source","blur":"","bounds":"[53,38][1280,122]","checkable":"false","checked":"false","clickable":"false","clip":"false","description":"","displayId":"0","enabled":"true","focused":"false","hashcode":"1:927","hierarchy":"ROOT21,0,0,0,0,3,1,0","hint":"","hitTestBehavior":"HitTestMode.Default","hostWindowId":"21","id":"","key":"","longClickable":"false","opacity":"1.000000","origBounds":"[53,38][1333,122]","originalText":"","scrollable":"false","selected":"false","text":"","type":"RelativeContainer","visible":"true","zIndex":"0"},"children":[{"attributes":{"accessibilityId":"981","backgroundColor":"#00000000","backgroundImage":"empty source","blur":"","bounds":"[53,38][192,122]","checkable":"false","checked":"false","clickable":"false","clip":"false","description":"","displayId":"0","enabled":"true","focused":"false","hashcode":"1:981","hierarchy":"ROOT21,0,0,0,0,3,1,0,1","hint":"","hitTestBehavior":"HitTestMode.Default","hostWindowId":"21","id":"StatusBarIconWrapper_status_bar_clock","key":"StatusBarIconWrapper_status_bar_clock","longClickable":"false","opacity":"1.000000","origBounds":"[53,38][192,122]","originalText":"","scrollable":"false","selected":"false","text":"","type":"Stack","visible":"true","zIndex":"0"},"children":[{"attributes":{"accessibilityId":"995","backgroundColor":"#00000000","backgroundImage":"empty source","blur":"","bounds":"[53,38][192,122]","checkable":"false","checked":"false","clickable":"false","clip":"false","description":"","displayId":"0","enabled":"true","focused":"false","hashcode":"1:995","hierarchy":"ROOT21,0,0,0,0,3,1,0,1,0","hint":"","hitTestBehavior":"HitTestMode.Default","hostWindowId":"21","id":"","key":"","longClickable":"false","opacity":"1.000000","origBounds":"[53,38][192,122]","originalText":"","scrollable":"false","selected":"false","text":"","type":"Row","visible":"true","zIndex":"0"},"children":[{"attributes":{"accessibilityId":"996","backgroundColor":"#00000000","backgroundImage":"empty source","blur":"","bounds":"[53,38][192,122]","checkable":"false","checked":"false","clickable":"false","clip":"false","description":"","displayId":"0","enabled":"true","focused":"false","hashcode":"1:996","hierarchy":"ROOT21,0,0,0,0,3,1,0,1,0,0","hint":"","hitTestBehavior":"HitTestMode.Default","hostWindowId":"21","id":"ClockStatusView","key":"ClockStatusView","longClickable":"false","opacity":"1.000000","origBounds":"[53,38][192,122]","originalText":"","scrollable":"false","selected":"false","text":"12, :, 45","type":"Flex","visible":"true","zIndex":"0"},"children":[{"attributes":{"accessibilityId":"997","backgroundColor":"#00000000","backgroundImage":"empty source","blur":"","bounds":"[53,49][130,111]","checkable":"false","checked":"false","clickable":"false","clip":"false","description":"","displayId":"0","enabled":"true","focused":"false","hashcode":"1:997","hierarchy":"ROOT21,0,0,0,0,3,1,0,1,0,0,0","hint":"","hitTestBehavior":"HitTestMode.Default","hostWindowId":"21","id":"","key":"","longClickable":"false","opacity":"1.000000","origBounds":"[53,49][130,111]","originalText":"","scrollable":"false","selected":"false","text":"","type":"Row","visible":"true","zIndex":"0"},"children":[{"attributes":{"accessibilityId":"998","backgroundColor":"#00000000","backgroundImage":"empty source","blur":"","bounds":"[53,49][115,111]","checkable":"false","checked":"false","clickable":"false","clip":"false","description":"","displayId":"0","enabled":"true","focused":"false","hashcode":"1:998","hierarchy":"ROOT21,0,0,0,0,3,1,0,1,0,0,0,0","hint":"","hitTestBehavior":"HitTestMode.Default","hostWindowId":"21","id":"TimeView_Text_timeText","key":"TimeView_Text_timeText","longClickable":"false","opacity":"1.000000","origBounds":"[53,49][115,111]","originalText":"","scrollable":"false","selected":"false","text":"","type":"TextClock","visible":"true","zIndex":"0"},"children":[{"attributes":{"accessibilityId":"999","backgroundColor":"#00000000","backgroundImage":"empty source","blur":"","bounds":"[53,49][115,111]","checkable":"false","checked":"false","clickable":"false","clip":"false","description":"","displayId":"0","enabled":"true","focused":"false","hashcode":"1:999","hierarchy":"ROOT21,0,0,0,0,3,1,0,1,0,0,0,0,0","hint":"","hitTestBehavior":"HitTestMode.Default","hostWindowId":"21","id":"","key":"","longClickable":"false","opacity":"1.000000","origBounds":"[53,49][115,111]","originalText":"12","scrollable":"false","selected":"false","text":"12","type":"Text","visible":"true","zIndex":"0"},"children":[]}]},{"attributes":{"accessibilityId":"1000","backgroundColor":"#00000000","backgroundImage":"empty source","blur":"","bounds":"[115,54][130,107]","checkable":"false","checked":"false","clickable":"false","clip":"false","description":"","displayId":"0","enabled":"true","focused":"false","hashcode":"1:1000","hierarchy":"ROOT21,0,0,0,0,3,1,0,1,0,0,0,1","hint":"","hitTestBehavior":"HitTestMode.Default","hostWindowId":"21","id":"TimeView_Text_timeText","key":"TimeView_Text_timeText","longClickable":"false","opacity":"1.000000","origBounds":"[115,54][130,107]","originalText":":","scrollable":"false","selected":"false","text":":","type":"Text","visible":"true","zIndex":"0"},"children":[]}]},{"attributes":{"accessibilityId":"1001","backgroundColor":"#00000000","backgroundImage":"empty source","blur":"","bounds":"[130,49][192,111]","checkable":"false","checked":"false","clickable":"false","clip":"false","description":"","displayId":"0","enabled":"true","focused":"false","hashcode":"1:1001","hierarchy":"ROOT21,0,0,0,0,3,1,0,1,0,0,1","hint":"","hitTestBehavior":"HitTestMode.Default","hostWindowId":"21","id":"TimeView_Text_timeText","key":"TimeView_Text_timeText","longClickable":"false","opacity":"1.000000","origBounds":"[130,49][192,111]","originalText":"","scrollable":"false","selected":"false","text":"","type":"TextClock","visible":"true","zIndex":"0"},"children":[{"attributes":{"accessibilityId":"1002","backgroundColor":"#00000000","backgroundImage":"empty source","blur":"","bounds":"[130,49][192,111]","checkable":"false","checked":"false","clickable":"false","clip":"false","description":"","displayId":"0","enabled":"true","focused":"false","hashcode":"1:1002","hierarchy":"ROOT21,0,0,0,0,3,1,0,1,0,0,1,0","hint":"","hitTestBehavior":"HitTestMode.Default","hostWindowId":"21","id":"","key":"","longClickable":"false","opacity":"1.000000","origBounds":"[130,49][192,111]","originalText":"45","scrollable":"false","selected":"false","text":"45","type":"Text","visible":"true","zIndex":"0"},"children":[]}]}]}]}]}]}]},{"attributes":{"accessibilityId":"939","backgroundColor":"#00000000","backgroundImage":"empty source","blur":"","bounds":"[0,38][1228,122]","checkable":"false","checked":"false","clickable":"false","clip":"false","description":"","displayId":"0","enabled":"true","focused":"false","hashcode":"1:939","hierarchy":"ROOT21,0,0,0,0,3,2","hint":"","hitTestBehavior":"HitTestMode.None","hostWindowId":"21","id":"sbg_right","key":"sbg_right","longClickable":"false","opacity":"1.000000","origBounds":"[-52,38][1228,122]","originalText":"","scrollable":"false","selected":"false","text":"","type":"RelativeContainer","visible":"true","zIndex":"0"},"children":[{"attributes":{"accessibilityId":"1468","backgroundColor":"#00000000","backgroundImage":"empty source","blur":"","bounds":"[952,38][1036,122]","checkable":"false","checked":"false","clickable":"false","clip":"false","description":"","displayId":"0","enabled":"true","focused":"false","hashcode":"1:1468","hierarchy":"ROOT21,0,0,0,0,3,2,0","hint":"","hitTestBehavior":"HitTestMode.Default","hostWindowId":"21","id":"StatusBarIconWrapper_status_bar_ethernet","key":"StatusBarIconWrapper_status_bar_ethernet","longClickable":"false","opacity":"1.000000","origBounds":"[952,38][1036,122]","originalText":"","scrollable":"false","selected":"false","text":"","type":"Stack","visible":"true","zIndex":"0"},"children":[{"attributes":{"accessibilityId":"1472","backgroundColor":"#00000000","backgroundImage":"empty source","blur":"","bounds":"[959,38][1036,122]","checkable":"false","checked":"false","clickable":"false","clip":"false","description":"","displayId":"0","enabled":"true","focused":"false","hashcode":"1:1472","hierarchy":"ROOT21,0,0,0,0,3,2,0,0","hint":"","hitTestBehavior":"HitTestMode.Default","hostWindowId":"21","id":"","key":"","longClickable":"false","opacity":"1.000000","origBounds":"[959,38][1036,122]","originalText":"","scrollable":"false","selected":"false","text":"","type":"Row","visible":"true","zIndex":"0"},"children":[{"attributes":{"accessibilityId":"1473","backgroundColor":"#00000000","backgroundImage":"empty source","blur":"","bounds":"[959,52][1036,108]","checkable":"false","checked":"false","clickable":"false","clip":"false","description":"","displayId":"0","enabled":"true","focused":"false","hashcode":"1:1473","hierarchy":"ROOT21,0,0,0,0,3,2,0,0,0","hint":"","hitTestBehavior":"HitTestMode.Default","hostWindowId":"21","id":"StatusBarIconItemEthernetComponent_Image_icon","key":"StatusBarIconItemEthernetComponent_Image_icon","longClickable":"false","opacity":"1.000000","origBounds":"[959,52][1036,108]","originalText":"","scrollable":"false","selected":"false","text":"","type":"SymbolGlyph","visible":"true","zIndex":"0"},"children":[]}]}]},{"attributes":{"accessibilityId":"1057","backgroundColor":"#00000000","backgroundImage":"empty source","blur":"","bounds":"[1036,38][1123,122]","checkable":"false","checked":"false","clickable":"false","clip":"false","description":"","displayId":"0","enabled":"true","focused":"false","hashcode":"1:1057","hierarchy":"ROOT21,0,0,0,0,3,2,1","hint":"","hitTestBehavior":"HitTestMode.Default","hostWindowId":"21","id":"StatusBarIconWrapper_status_bar_signal","key":"StatusBarIconWrapper_status_bar_signal","longClickable":"false","opacity":"1.000000","origBounds":"[1036,38][1123,122]","originalText":"","scrollable":"false","selected":"false","text":"","type":"Stack","visible":"true","zIndex":"0"},"children":[{"attributes":{"accessibilityId":"1125","backgroundColor":"#00000000","backgroundImage":"empty source","blur":"","bounds":"[1043,38][1123,122]","checkable":"false","checked":"false","clickable":"false","clip":"false","description":"","displayId":"0","enabled":"true","focused":"false","hashcode":"1:1125","hierarchy":"ROOT21,0,0,0,0,3,2,1,0","hint":"","hitTestBehavior":"HitTestMode.Default","hostWindowId":"21","id":"","key":"","longClickable":"false","opacity":"1.000000","origBounds":"[1043,38][1123,122]","originalText":"","scrollable":"false","selected":"false","text":"","type":"Row","visible":"true","zIndex":"0"},"children":[{"attributes":{"accessibilityId":"1130","backgroundColor":"#00000000","backgroundImage":"empty source","blur":"","bounds":"[1043,52][1123,108]","checkable":"false","checked":"false","clickable":"false","clip":"false","description":"","displayId":"0","enabled":"true","focused":"false","hashcode":"1:1130","hierarchy":"ROOT21,0,0,0,0,3,2,1,0,0","hint":"","hitTestBehavior":"HitTestMode.Default","hostWindowId":"21","id":"","key":"","longClickable":"false","opacity":"1.000000","origBounds":"[1043,52][1123,108]","originalText":"","scrollable":"false","selected":"false","text":"","type":"Stack","visible":"true","zIndex":"0"},"children":[{"attributes":{"accessibilityId":"1131","backgroundColor":"#00000000","backgroundImage":"empty source","blur":"","bounds":"[1043,52][1123,108]","checkable":"false","checked":"false","clickable":"false","clip":"false","description":"","displayId":"0","enabled":"true","focused":"false","hashcode":"1:1131","hierarchy":"ROOT21,0,0,0,0,3,2,1,0,0,0","hint":"","hitTestBehavior":"HitTestMode.Default","hostWindowId":"21","id":"SignalComponent-SignalIcon_Image_cellular","key":"SignalComponent-SignalIcon_Image_cellular","longClickable":"false","opacity":"1.000000","origBounds":"[1043,52][1123,108]","originalText":"","scrollable":"false","selected":"false","text":"","type":"SymbolGlyph","visible":"true","zIndex":"0"},"children":[]},{"attributes":{"accessibilityId":"1132","backgroundColor":"#00000000","backgroundImage":"empty source","blur":"","bounds":"[1043,52][1123,108]","checkable":"false","checked":"false","clickable":"false","clip":"false","description":"","displayId":"0","enabled":"true","focused":"false","hashcode":"1:1132","hierarchy":"ROOT21,0,0,0,0,3,2,1,0,0,1","hint":"","hitTestBehavior":"HitTestMode.Default","hostWindowId":"21","id":"SignalComponent-SignalIcon_Image_cellularImage","key":"SignalComponent-SignalIcon_Image_cellularImage","longClickable":"false","opacity":"1.000000","origBounds":"[1043,52][1123,108]","originalText":"","scrollable":"false","selected":"false","text":"","type":"SymbolGlyph","visible":"true","zIndex":"0"},"children":[]}]}]}]},{"attributes":{"accessibilityId":"1060","backgroundColor":"#00000000","backgroundImage":"empty source","blur":"","bounds":"[1123,38][1228,122]","checkable":"false","checked":"false","clickable":"false","clip":"false","description":"","displayId":"0","enabled":"true","focused":"false","hashcode":"1:1060","hierarchy":"ROOT21,0,0,0,0,3,2,2","hint":"","hitTestBehavior":"HitTestMode.Default","hostWindowId":"21","id":"StatusBarIconWrapper_status_bar_battery","key":"StatusBarIconWrapper_status_bar_battery","longClickable":"false","opacity":"1.000000","origBounds":"[1123,38][1228,122]","originalText":"","scrollable":"false","selected":"false","text":"","type":"Stack","visible":"true","zIndex":"0"},"children":[{"attributes":{"accessibilityId":"1064","backgroundColor":"#00000000","backgroundImage":"empty source","blur":"","bounds":"[1130,38][1228,122]","checkable":"false","checked":"false","clickable":"false","clip":"false","description":"","displayId":"0","enabled":"true","focused":"false","hashcode":"1:1064","hierarchy":"ROOT21,0,0,0,0,3,2,2,0","hint":"","hitTestBehavior":"HitTestMode.Default","hostWindowId":"21","id":"BatteryComponent-batteryIcon_Image_batteryIcon","key":"BatteryComponent-batteryIcon_Image_batteryIcon","longClickable":"false","opacity":"1.000000","origBounds":"[1130,38][1228,122]","originalText":"","scrollable":"false","selected":"false","text":"","type":"Row","visible":"true","zIndex":"0"},"children":[{"attributes":{"accessibilityId":"1065","backgroundColor":"#00000000","backgroundImage":"empty source","blur":"","bounds":"[1130,52][1228,108]","checkable":"false","checked":"false","clickable":"false","clip":"false","description":"","displayId":"0","enabled":"true","focused":"false","hashcode":"1:1065","hierarchy":"ROOT21,0,0,0,0,3,2,2,0,0","hint":"","hitTestBehavior":"HitTestMode.Default","hostWindowId":"21","id":"","key":"","longClickable":"false","opacity":"1.000000","origBounds":"[1130,52][1228,108]","originalText":"","scrollable":"false","selected":"false","text":"","type":"Stack","visible":"true","zIndex":"0"},"children":[{"attributes":{"accessibilityId":"1067","backgroundColor":"#00000000","backgroundImage":"empty source","blur":"","bounds":"[1130,52][1228,108]","checkable":"false","checked":"false","clickable":"false","clip":"false","description":"","displayId":"0","enabled":"true","focused":"false","hashcode":"1:1067","hierarchy":"ROOT21,0,0,0,0,3,2,2,0,0,0","hint":"","hitTestBehavior":"HitTestMode.Default","hostWindowId":"21","id":"","key":"","longClickable":"false","opacity":"1.000000","origBounds":"[1130,52][1228,108]","originalText":"","scrollable":"false","selected":"false","text":"","type":"Stack","visible":"true","zIndex":"0"},"children":[{"attributes":{"accessibilityId":"1068","backgroundColor":"#00000000","backgroundImage":"empty source","blur":"","bounds":"[1130,52][1228,108]","checkable":"false","checked":"false","clickable":"false","clip":"false","description":"","displayId":"0","enabled":"true","focused":"false","hashcode":"1:1068","hierarchy":"ROOT21,0,0,0,0,3,2,2,0,0,0,0","hint":"","hitTestBehavior":"HitTestMode.Default","hostWindowId":"21","id":"BatteryComponent-batteryIcon_Image_batteryBorder","key":"BatteryComponent-batteryIcon_Image_batteryBorder","longClickable":"false","opacity":"1.000000","origBounds":"[1130,52][1228,108]","originalText":"","scrollable":"false","selected":"false","text":"","type":"SymbolGlyph","visible":"true","zIndex":"0"},"children":[]},{"attributes":{"accessibilityId":"1070","backgroundColor":"#00000000","backgroundImage":"empty source","blur":"","bounds":"[1139,58][1209,103]","checkable":"false","checked":"false","clickable":"false","clip":"false","description":"","displayId":"0","enabled":"true","focused":"false","hashcode":"1:1070","hierarchy":"ROOT21,0,0,0,0,3,2,2,0,0,0,1","hint":"","hitTestBehavior":"HitTestMode.Default","hostWindowId":"21","id":"BatteryComponent-batteryIcon_Text_batterySoc","key":"BatteryComponent-batteryIcon_Text_batterySoc","longClickable":"false","opacity":"1.000000","origBounds":"[1139,58][1209,103]","originalText":"100","scrollable":"false","selected":"false","text":"100","type":"Text","visible":"true","zIndex":"0"},"children":[]}]}]}]}]}]}]},{"attributes":{"accessibilityId":"1219","backgroundColor":"#00000000","backgroundImage":"empty source","blur":"","bounds":"[457,31][823,129]","checkable":"false","checked":"false","clickable":"false","clip":"false","description":"","displayId":"0","enabled":"true","focused":"false","hashcode":"1:1219","hierarchy":"ROOT21,0,0,0,0,4","hint":"","hitTestBehavior":"HitTestMode.Default","hostWindowId":"21","id":"StatusBarView_LiveCapsuleListContainer","key":"StatusBarView_LiveCapsuleListContainer","longClickable":"false","opacity":"1.000000","origBounds":"[457,31][823,129]","originalText":"","scrollable":"false","selected":"false","text":"","type":"Stack","visible":"true","zIndex":"0"},"children":[{"attributes":{"accessibilityId":"1221","backgroundColor":"#00000000","backgroundImage":"empty source","blur":"","bounds":"[457,31][823,129]","checkable":"false","checked":"false","clickable":"false","clip":"false","description":"","displayId":"0","enabled":"true","focused":"false","hashcode":"1:1221","hierarchy":"ROOT21,0,0,0,0,4,0","hint":"","hitTestBehavior":"HitTestMode.Default","hostWindowId":"21","id":"[Live]LiveCapsuleListView","key":"[Live]LiveCapsuleListView","longClickable":"false","opacity":"1.000000","origBounds":"[457,31][823,129]","originalText":"","scrollable":"false","selected":"false","text":"","type":"Stack","visible":"true","zIndex":"0"},"children":[{"attributes":{"accessibilityId":"1226","backgroundColor":"#00000000","backgroundImage":"empty source","blur":"","bounds":"[274,2][1006,136]","checkable":"false","checked":"false","clickable":"true","clip":"false","description":"","displayId":"0","enabled":"true","focused":"false","hashcode":"1:1226","hierarchy":"ROOT21,0,0,0,0,4,0,0","hint":"","hitTestBehavior":"HitTestMode.None","hostWindowId":"21","id":"LiveMetaBallBaseVm","key":"LiveMetaBallBaseVm","longClickable":"false","opacity":"0.000000","origBounds":"[274,2][1006,159]","originalText":"","scrollable":"false","selected":"false","text":"","type":"metaballNode","visible":"true","zIndex":"0"},"children":[]}]}]}]}]}]}]}]}]}